pac_hunter/__init__.py
pac_hunter/hunter.py
pac_hunter/states.py
pac_hunter-0.1.2.dist-info/LICENSE
pac_hunter-0.1.2.dist-info/WHEEL
pac_hunter-0.1.2.dist-info/METADATA
pac_hunter-0.1.2.dist-info/RECORD
