Metadata-Version: 2.1
Name: pac-hunter
Version: 0.1.2
Summary: Search donations from specific PACs to candidates of interest, using OpenFEC and fivethirtyeight data
License: MIT
Author: jlwhelan28
Author-email: jlwhelan28@gmail.com
Requires-Python: >=3.7,<4.0
Classifier: License :: OSI Approved :: MIT License
Classifier: Programming Language :: Python :: 3
Classifier: Programming Language :: Python :: 3.7
Classifier: Programming Language :: Python :: 3.8
Classifier: Programming Language :: Python :: 3.9
Classifier: Programming Language :: Python :: 3.10
Classifier: Programming Language :: Python :: 3.11
Requires-Dist: httpx (>=0.23,<0.24)
Requires-Dist: pandas (>=1.0,<2.0)
Requires-Dist: requests (>=2.28,<3.0)
Requires-Dist: seaborn (>=0.12,<0.13)
Requires-Dist: thefuzz (>=0.19,<0.20)
